rcxxxx_tm_lib.py
sst25vf.py
tekon_zeromq.py
tekwi.py
tekon_libraries-1.0.0.dist-info/METADATA
tekon_libraries-1.0.0.dist-info/WHEEL
tekon_libraries-1.0.0.dist-info/top_level.txt
tekon_libraries-1.0.0.dist-info/RECORD
