Metadata-Version: 2.1
Name: tekon-libraries
Version: 1.0.0
Summary: Tekon Python Libraries.
Home-page: UNKNOWN
Author: UNKNOWN
Author-email: UNKNOWN
License: UNKNOWN
Platform: UNKNOWN
